csaf_vex/__init__.py
csaf_vex/builder/__init__.py
csaf_vex/builder/csafvex.py
csaf_vex/cli.py
csaf_vex/models/__init__.py
csaf_vex/models/common.py
csaf_vex/models/csafvex.py
csaf_vex/models/document.py
csaf_vex/models/product_tree.py
csaf_vex/models/vulnerability.py
csaf_vex/py.typed
csaf_vex/validation/__init__.py
csaf_vex/validation/base.py
csaf_vex/validation/manager.py
csaf_vex/validation/result.py
csaf_vex/validation/validator.py
csaf_vex/verification/__init__.py
csaf_vex/verification/csaf_compliance.py
csaf_vex/verification/data_type_checks.py
csaf_vex/verification/result.py
csaf_vex/verification/schemas/__init__.py
csaf_vex/verification/schemas/csaf_2_0.json
csaf_vex/verification/schemas/cvss_v2_0.json
csaf_vex/verification/schemas/cvss_v3_0.json
csaf_vex/verification/schemas/cvss_v3_1.json
csaf_vex/verification/verifier.py
csaf_vex-0.1.0b5.dist-info/WHEEL
csaf_vex-0.1.0b5.dist-info/entry_points.txt
csaf_vex-0.1.0b5.dist-info/METADATA
csaf_vex-0.1.0b5.dist-info/RECORD
