Metadata-Version: 2.3
Name: csaf-vex
Version: 0.1.0b5
Summary: A library for generating, parsing and validating CSAF VEX files
Keywords: csaf,vex,security,vulnerability,advisory
Author: Jakub Frejlach, Juan Perez de Algaba, George Vauter
Author-email: Jakub Frejlach <jfrejlac@redhat.com>, Juan Perez de Algaba <jperezde@redhat.com>, George Vauter <gvauter@redhat.com>
License: MIT License
Classifier: Development Status :: 4 - Beta
Classifier: Intended Audience :: Developers
Classifier: License :: OSI Approved :: MIT License
Classifier: Operating System :: OS Independent
Classifier: Programming Language :: Python :: 3
Classifier: Programming Language :: Python :: 3.10
Classifier: Programming Language :: Python :: 3.11
Classifier: Programming Language :: Python :: 3.12
Classifier: Programming Language :: Python :: 3.13
Classifier: Topic :: Security
Classifier: Topic :: Software Development :: Libraries :: Python Modules
Requires-Dist: attrs>=25.4.0
Requires-Dist: click>=8.3.1
Requires-Dist: cvss>=3.0
Requires-Dist: jsonschema>=4.0.0
Requires-Dist: packageurl-python>=0.15.0
Requires-Python: >=3.11
